randgen/__init__.py
randgen/cli.py
randgen/generator.py
randgen_cli-0.1.0.dist-info/licenses/LICENSE
randgen_cli-0.1.0.dist-info/METADATA
randgen_cli-0.1.0.dist-info/WHEEL
randgen_cli-0.1.0.dist-info/entry_points.txt
randgen_cli-0.1.0.dist-info/top_level.txt
randgen_cli-0.1.0.dist-info/RECORD
