Metadata-Version: 2.4
Name: randgen-cli
Version: 0.1.0
Summary: A smart random data generator for testing and development.
Author-email: fengjikui <1412414664@qq.com>
License: MIT License
Classifier: License :: OSI Approved :: MIT License
Classifier: Programming Language :: Python :: 3
Classifier: Programming Language :: Python :: 3.7
Classifier: Programming Language :: Python :: 3.8
Classifier: Programming Language :: Python :: 3.9
Classifier: Programming Language :: Python :: 3.10
Classifier: Programming Language :: Python :: 3.11
Requires-Python: >=3.7
License-File: LICENSE
Requires-Dist: Faker>=15.0.0
Dynamic: license-file
